sage/platform/__init__.py
sage/platform/_version.py
sage/platform/utils.py
sage/platform/queue/__init__.py
sage/platform/queue/base_queue_descriptor.py
sage/platform/queue/python_queue_descriptor.py
sage/platform/queue/ray_queue_descriptor.py
sage/platform/queue/rpc_queue_descriptor.py
sage/platform/service/__init__.py
sage/platform/service/base_service.py
sage/platform/storage/__init__.py
sage/platform/storage/base_kv_backend.py
sage/platform/storage/dict_kv_backend.py
sage/platform/storage/hdfs_config.py
sage/platform/storage/hdfs_filesystem.py
isage_platform-0.2.3.4.dist-info/METADATA
isage_platform-0.2.3.4.dist-info/WHEEL
isage_platform-0.2.3.4.dist-info/top_level.txt
isage_platform-0.2.3.4.dist-info/RECORD
