Metadata-Version: 2.4
Name: isage-platform
Version: 0.2.3.4
Summary: SAGE Platform Services - Queue, Storage, and Service Abstractions
Author-email: IntelliStream Team <shuhao_zhang@hust.edu.cn>
License: MIT
Project-URL: Homepage, https://github.com/sage-ai/sage
Project-URL: Documentation, https://sage-ai.org/docs
Project-URL: Repository, https://github.com/sage-ai/sage
Project-URL: Issues, https://github.com/sage-ai/sage/issues
Keywords: ai,sage,platform,queue,storage,infrastructure
Classifier: Development Status :: 4 - Beta
Classifier: Intended Audience :: Developers
Classifier: Operating System :: OS Independent
Classifier: Programming Language :: Python :: 3
Classifier: Programming Language :: Python :: 3.8
Classifier: Programming Language :: Python :: 3.9
Classifier: Programming Language :: Python :: 3.10
Classifier: Programming Language :: Python :: 3.11
Classifier: Topic :: Scientific/Engineering :: Artificial Intelligence
Requires-Python: >=3.8
Requires-Dist: ray[client]<3.0.0,>=2.48.0
Requires-Dist: paramiko<4.0.0,>=3.5.0
Requires-Dist: fabric<4.0.0,>=3.2.0
Provides-Extra: dev
Requires-Dist: pytest>=7.4.0; extra == "dev"
Requires-Dist: pytest-cov>=4.0.0; extra == "dev"
Requires-Dist: pytest-asyncio>=0.21.0; extra == "dev"
Requires-Dist: ruff==0.14.6; extra == "dev"
Requires-Dist: mypy>=1.7.0; extra == "dev"
Provides-Extra: all
